{
  "lastUpdated": "2026-01-27",
  "phrases": [
    { "id": "t1", "category": "Tickets", "pl": "Bilet", "en": "Ticket", "level": 7 },
    { "id": "t2", "category": "Tickets", "pl": "Bilet powrotny", "en": "Return ticket", "level": 7 },
    { "id": "t3", "category": "Tickets", "pl": "Poproszę dwa bilety", "en": "Two tickets, please", "level": 7 },
    { "id": "t4", "category": "Tickets", "pl": "Zniżka studencka", "en": "Student discount", "level": 7 },
    { "id": "t5", "category": "Tickets", "pl": "Gdzie mogę kupić bilet?", "en": "Where can I buy a ticket?", "level": 7 },
    { "id": "t6", "category": "Tickets", "pl": "Kasa biletowa", "en": "Ticket office", "level": 7 },
    { "id": "t7", "category": "Tickets", "pl": "Automat biletowy", "en": "Ticket machine", "level": 7 },
    { "id": "t8", "category": "Tickets", "pl": "Czy ten bilet jest ważny?", "en": "Is this ticket valid?", "level": 7 },
    { "id": "t9", "category": "Tickets", "pl": "Kontrola biletów", "en": "Ticket inspection", "level": 7 },
    { "id": "t10", "category": "Tickets", "pl": "Miejsce rezerwowane", "en": "Reserved seat", "level": 7 },

    { "id": "tr11", "category": "Trains & Buses", "pl": "Pociąg", "en": "Train", "level": 7 },
    { "id": "tr12", "category": "Trains & Buses", "pl": "Autobus", "en": "Bus", "level": 7 },
    { "id": "tr13", "category": "Trains & Buses", "pl": "Tramwaj", "en": "Tram", "level": 7 },
    { "id": "tr14", "category": "Trains & Buses", "pl": "Peron", "en": "Platform", "level": 7 },
    { "id": "tr15", "category": "Trains & Buses", "pl": "Tor", "en": "Track", "level": 7 },
    { "id": "tr16", "category": "Trains & Buses", "pl": "O której odjeżdża pociąg?", "en": "What time does the train leave?", "level": 7 },
    { "id": "tr17", "category": "Trains & Buses", "pl": "O której przyjeżdża autobus?", "en": "What time does the bus arrive?", "level": 7 },
    { "id": "tr18", "category": "Trains & Buses", "pl": "Czy to jest bezpośredni pociąg?", "en": "Is this a direct train?", "level": 7 },
    { "id": "tr19", "category": "Trains & Buses", "pl": "Muszę się przesiąść", "en": "I have to change (transfer)", "level": 7 },
    { "id": "tr20", "category": "Trains & Buses", "pl": "Opóźnienie", "en": "Delay", "level": 7 },

    { "id": "a21", "category": "Airport", "pl": "Samolot", "en": "Airplane", "level": 7 },
    { "id": "a22", "category": "Airport", "pl": "Karta pokładowa", "en": "Boarding pass", "level": 7 },
    { "id": "a23", "category": "Airport", "pl": "Bagaż", "en": "Luggage", "level": 7 },
    { "id": "a24", "category": "Airport", "pl": "Odprawa", "en": "Check-in", "level": 7 },
    { "id": "a25", "category": "Airport", "pl": "Kontrola bezpieczeństwa", "en": "Security check", "level": 7 },
    { "id": "a26", "category": "Airport", "pl": "Bramka", "en": "Gate", "level": 7 },
    { "id": "a27", "category": "Airport", "pl": "Lot odwołany", "en": "Flight cancelled", "level": 7 },
    { "id": "a28", "category": "Airport", "pl": "Gdzie jest odbiór bagażu?", "en": "Where is baggage claim?", "level": 7 },
    { "id": "a29", "category": "Airport", "pl": "Paszyport, proszę", "en": "Passport, please", "level": 7 },
    { "id": "a30", "category": "Airport", "pl": "Mam tylko bagaż podręczny", "en": "I only have carry-on luggage", "level": 7 },

    { "id": "h31", "category": "Hotel", "pl": "Mam rezerwację", "en": "I have a reservation", "level": 7 },
    { "id": "h32", "category": "Hotel", "pl": "Czy są wolne pokoje?", "en": "Are there free rooms?", "level": 7 },
    { "id": "h33", "category": "Hotel", "pl": "Pokój jednoosobowy", "en": "Single room", "level": 7 },
    { "id": "h34", "category": "Hotel", "pl": "Pokój dwuosobowy", "en": "Double room", "level": 7 },
    { "id": "h35", "category": "Hotel", "pl": "Czy śniadanie jest wliczone?", "en": "Is breakfast included?", "level": 7 },
    { "id": "h36", "category": "Hotel", "pl": "O której jest wymeldowanie?", "en": "What time is check-out?", "level": 7 },
    { "id": "h37", "category": "Hotel", "pl": "Hasło do Wi-Fi", "en": "Wi-Fi password", "level": 7 },
    { "id": "h38", "category": "Hotel", "pl": "Czy mogę zostawić bagaż?", "en": "Can I leave my luggage?", "level": 7 },
    { "id": "h39", "category": "Hotel", "pl": "Klimatyzacja nie działa", "en": "Air conditioning doesn't work", "level": 7 },
    { "id": "h40", "category": "Hotel", "pl": "Klucz do pokoju", "en": "Room key", "level": 7 },

    { "id": "c41", "category": "City Navigation", "pl": "Gdzie jest centrum?", "en": "Where is the center?", "level": 7 },
    { "id": "c42", "category": "City Navigation", "pl": "Jak dojechać do...?", "en": "How to get to...?", "level": 7 },
    { "id": "c43", "category": "City Navigation", "pl": "To jest blisko stąd", "en": "It is close to here", "level": 7 },
    { "id": "c44", "category": "City Navigation", "pl": "To jest daleko", "en": "It is far", "level": 7 },
    { "id": "c45", "category": "City Navigation", "pl": "Idź prosto", "en": "Go straight", "level": 7 },
    { "id": "c46", "category": "City Navigation", "pl": "Skręć w lewo / w prawo", "en": "Turn left / right", "level": 7 },
    { "id": "c47", "category": "City Navigation", "pl": "Mapa miasta", "en": "City map", "level": 7 },
    { "id": "c48", "category": "City Navigation", "pl": "Przystanek autobusowy", "en": "Bus stop", "level": 7 },
    { "id": "c49", "category": "City Navigation", "pl": "Stacja metra", "en": "Metro station", "level": 7 },
    { "id": "c50", "category": "City Navigation", "pl": "Taxi / Taksówka", "en": "Taxi", "level": 7 },

    { "id": "d51", "category": "Driving", "pl": "Samochód", "en": "Car", "level": 7 },
    { "id": "d52", "category": "Driving", "pl": "Prawo jazdy", "en": "Driving license", "level": 7 },
    { "id": "d53", "category": "Driving", "pl": "Wypożyczalnia samochodów", "en": "Car rental", "level": 7 },
    { "id": "d54", "category": "Driving", "pl": "Stacja paliw", "en": "Petrol station", "level": 7 },
    { "id": "d55", "category": "Driving", "pl": "Benzyna / Diesel", "en": "Petrol / Diesel", "level": 7 },
    { "id": "d56", "category": "Driving", "pl": "Parking", "en": "Parking", "level": 7 },
    { "id": "d57", "category": "Driving", "pl": "Korek", "en": "Traffic jam", "level": 7 },
    { "id": "d58", "category": "Driving", "pl": "Autostrada", "en": "Highway", "level": 7 },
    { "id": "d59", "category": "Driving", "pl": "Opony zimowe", "en": "Winter tires", "level": 7 },
    { "id": "d60", "category": "Driving", "pl": "Mandat", "en": "Traffic fine", "level": 7 },

    { "id": "u61", "category": "Useful Verbs", "pl": "Podróżować", "en": "To travel", "level": 7 },
    { "id": "u62", "category": "Useful Verbs", "pl": "Zwiedzać", "en": "To sightsee", "level": 7 },
    { "id": "u63", "category": "Useful Verbs", "pl": "Rezerwować", "en": "To book / reserve", "level": 7 },
    { "id": "u64", "category": "Useful Verbs", "pl": "Kupować", "en": "To buy", "level": 7 },
    { "id": "u65", "category": "Useful Verbs", "pl": "Płacić", "en": "To pay", "level": 7 },
    { "id": "u66", "category": "Useful Verbs", "pl": "Szukać", "en": "To look for", "level": 7 },
    { "id": "u67", "category": "Useful Verbs", "pl": "Znaleźć", "en": "To find", "level": 7 },
    { "id": "u68", "category": "Useful Verbs", "pl": "Czekać", "en": "To wait", "level": 7 },
    { "id": "u69", "category": "Useful Verbs", "pl": "Jechać", "en": "To go (by vehicle)", "level": 7 },
    { "id": "u70", "category": "Useful Verbs", "pl": "Lecieć", "en": "To fly", "level": 7 }
  ]
}
